crawlab_demo/__init__.py
crawlab_demo/demo.py
crawlab_demo/actions/__init__.py
crawlab_demo/actions/cleanup.py
crawlab_demo/actions/import_demo.py
crawlab_demo/actions/reimport_demo.py
crawlab_demo/actions/validate.py
crawlab_demo/cli/__init__.py
crawlab_demo/cli/main.py
crawlab_demo/data/demo.json
crawlab_demo/data/spiders/golang/basic/crawlab.json
crawlab_demo/data/spiders/golang/basic/go.mod
crawlab_demo/data/spiders/golang/basic/go.sum
crawlab_demo/data/spiders/golang/basic/main.go
crawlab_demo/data/spiders/golang/colly_scrapy_docs/crawlab.json
crawlab_demo/data/spiders/golang/colly_scrapy_docs/go.mod
crawlab_demo/data/spiders/golang/colly_scrapy_docs/go.sum
crawlab_demo/data/spiders/golang/colly_scrapy_docs/main.go
crawlab_demo/data/spiders/golang/rod_github/crawlab.json
crawlab_demo/data/spiders/golang/rod_github/go.mod
crawlab_demo/data/spiders/golang/rod_github/go.sum
crawlab_demo/data/spiders/golang/rod_github/main.go
crawlab_demo/data/spiders/node/basic/crawlab.json
crawlab_demo/data/spiders/node/basic/main.js
crawlab_demo/data/spiders/node/puppeteer_163_tech_news/crawlab.json
crawlab_demo/data/spiders/node/puppeteer_163_tech_news/main.js
crawlab_demo/data/spiders/python/basic/__init__.py
crawlab_demo/data/spiders/python/basic/crawlab.json
crawlab_demo/data/spiders/python/basic/main.py
crawlab_demo/data/spiders/python/bookdepository/crawlab.json
crawlab_demo/data/spiders/python/bookdepository/scrapy.cfg
crawlab_demo/data/spiders/python/bookdepository/bookdepository/__init__.py
crawlab_demo/data/spiders/python/bookdepository/bookdepository/items.py
crawlab_demo/data/spiders/python/bookdepository/bookdepository/middlewares.py
crawlab_demo/data/spiders/python/bookdepository/bookdepository/pipelines.py
crawlab_demo/data/spiders/python/bookdepository/bookdepository/settings.py
crawlab_demo/data/spiders/python/bookdepository/bookdepository/spiders/__init__.py
crawlab_demo/data/spiders/python/bookdepository/bookdepository/spiders/books.py
crawlab_demo-0.0.6.post12.dist-info/LICENSE
crawlab_demo-0.0.6.post12.dist-info/METADATA
crawlab_demo-0.0.6.post12.dist-info/WHEEL
crawlab_demo-0.0.6.post12.dist-info/entry_points.txt
crawlab_demo-0.0.6.post12.dist-info/top_level.txt
crawlab_demo-0.0.6.post12.dist-info/RECORD
