Metadata-Version: 2.1
Name: crawlab-demo
Version: 0.0.6.post12
Summary: Demo for Crawlab
Home-page: https://github.com/crawlab-team/crawlab-demo
Author: tikazyq
Author-email: tikazyq@163.com
License: BSD-3-Clause
Platform: UNKNOWN
Classifier: Programming Language :: Python :: 3
Classifier: License :: OSI Approved :: BSD License
Classifier: Operating System :: OS Independent
Requires-Dist: crawlab-sdk (>=0.6.0)
Requires-Dist: selenium
Requires-Dist: scrapy
Requires-Dist: playwright
